{
  "tokens": [
    {
      "token": "8187428272:AAGWLjh06SVBFl0aPXy9R9SjAPtMz4qBP4E",
      "expiry": "07-2025"
    },
    {
      "token": "your-bot-token-2",
      "expiry": "06-2025"
    },
    {
      "token": "your-bot-token-2",
      "expiry": "06-2025"
    },
    {
      "token": "your-bot-token-2",
      "expiry": "06-2025"
    },
    {
      "token": "your-bot-token-2",
      "expiry": "06-2025"
    },
    {
      "token": "your-bot-token-2",
      "expiry": "06-2025"
    },
    {
      "token": "your-bot-token-2",
      "expiry": "06-2025"
    },
    {
      "token": "your-bot-token-2",
      "expiry": "06-2025"
    },
    {
      "token": "your-bot-token-2",
      "expiry": "06-2025"
    },
    {
      "token": "your-bot-token-2",
      "expiry": "06-2025"
    },
    {
      "token": "your-bot-token-3",
      "expiry": "07-2025"
    }
  ]
}